toolkit/__init__.py
toolkit/cli.py
toolkit/core.py
toolkit/dashboard.py
toolkit/decorators.py
toolkit/logging.py
toolkit/replay.py
toolkit/server.py
toolkit/types.py
toolkit/webhooks.py
toolkit/static/app.js
toolkit/static/index.html
toolkit/static/styles.css
b2a_toolkit-0.1.3.dist-info/METADATA
b2a_toolkit-0.1.3.dist-info/WHEEL
b2a_toolkit-0.1.3.dist-info/entry_points.txt
b2a_toolkit-0.1.3.dist-info/licenses/LICENSE
b2a_toolkit-0.1.3.dist-info/RECORD
