Metadata-Version: 2.4
Name: b2a-toolkit
Version: 0.1.3
Summary: A lightweight framework to expose any API as an agent-compatible tool
Author-email: Toolkit Team <toolkit-founder@agenticflow.app>
License: Apache-2.0
License-File: LICENSE
Requires-Python: >=3.8
Requires-Dist: click>=8.1.0
Requires-Dist: fastapi>=0.109.0
Requires-Dist: openapi-spec-validator>=0.7.0
Requires-Dist: pydantic>=2.0.0
Requires-Dist: requests>=2.31.0
Requires-Dist: typing-extensions>=4.5.0
Requires-Dist: uvicorn>=0.27.0
